{
  "entity": "Ethiopian Electric Power",
  "report_title": "Independent Auditor's Report and Financial Statements",
  "period_end": "2024-07-07",
  "unit": "Birr'000",
  "currency": "ETB",
  "source_file": "2024.pdf",
  "statements": {
    "profit_or_loss_and_oci": {
      "as_at": [
        "2024-07-07",
        "2023-07-07"
      ],
      "line_items": [
        {
          "name": "Revenue from contracts with customers",
          "note": "5",
          "values": {
            "2024-07-07": 27137357,
            "2023-07-07": 22484423
          }
        },
        {
          "name": "Direct costs",
          "note": "6(a)",
          "values": {
            "2024-07-07": -7012928,
            "2023-07-07": -4076066
          }
        },
        {
          "name": "Operating expenses",
          "note": "6(b)",
          "values": {
            "2024-07-07": -792390,
            "2023-07-07": -451321
          }
        },
        {
          "name": "Net impairment gain (loss) on financial assets",
          "note": "13,15",
          "values": {
            "2024-07-07": -847818,
            "2023-07-07": -14176301
          }
        },
        {
          "name": "Other income",
          "note": "8",
          "values": {
            "2024-07-07": 5111622,
            "2023-07-07": 3271919
          }
        },
        {
          "name": "EBITDA",
          "note": null,
          "values": {
            "2024-07-07": 23595843,
            "2023-07-07": 7352654
          }
        },
        {
          "name": "Depreciation of property, plant and equipment",
          "note": "10",
          "values": {
            "2024-07-07": -8468768,
            "2023-07-07": -8034343
          }
        },
        {
          "name": "Depreciation charge of right of use asset",
          "note": "11",
          "values": {
            "2024-07-07": -40054,
            "2023-07-07": -122979
          }
        },
        {
          "name": "Total depreciation",
          "note": null,
          "values": {
            "2024-07-07": -8508822,
            "2023-07-07": -8157322
          }
        },
        {
          "name": "Operating profit/(loss)",
          "note": null,
          "values": {
            "2024-07-07": 15087021,
            "2023-07-07": -804668
          }
        },
        {
          "name": "Finance costs",
          "note": "9",
          "values": {
            "2024-07-07": -25234574,
            "2023-07-07": -24034129
          }
        },
        {
          "name": "Net loss for the year",
          "note": null,
          "values": {
            "2024-07-07": -10147553,
            "2023-07-07": -24838797
          }
        },
        {
          "name": "Remeasurement gain/(loss) on post employment benefits (OCI)",
          "note": "18",
          "values": {
            "2024-07-07": 17789,
            "2023-07-07": -34988
          }
        },
        {
          "name": "Total comprehensive loss for the period",
          "note": null,
          "values": {
            "2024-07-07": -10129764,
            "2023-07-07": -24873785
          }
        }
      ]
    },
    "financial_position": {
      "as_at": [
        "2024-07-07",
        "2023-07-07"
      ],
      "assets": {
        "non_current": [
          {
            "name": "Property, plant and equipment",
            "note": "10",
            "values": {
              "2024-07-07": 683138950,
              "2023-07-07": 635528154
            }
          },
          {
            "name": "Intangible assets",
            "note": "14",
            "values": {
              "2024-07-07": 645613,
              "2023-07-07": 368218
            }
          },
          {
            "name": "Right of use assets",
            "note": "11",
            "values": {
              "2024-07-07": 26585,
              "2023-07-07": 37030
            }
          },
          {
            "name": "Long term receivables",
            "note": "13(a)",
            "values": {
              "2024-07-07": null,
              "2023-07-07": 115428
            }
          },
          {
            "name": "Total non-current assets",
            "note": null,
            "values": {
              "2024-07-07": 683811148,
              "2023-07-07": 636048830
            }
          }
        ],
        "current": [
          {
            "name": "Inventories",
            "note": "12",
            "values": {
              "2024-07-07": 1889621,
              "2023-07-07": 490214
            }
          },
          {
            "name": "Trade and other receivables",
            "note": "13(b)",
            "values": {
              "2024-07-07": 20592162,
              "2023-07-07": 27708229
            }
          },
          {
            "name": "Cash and cash equivalents",
            "note": "16",
            "values": {
              "2024-07-07": 3453095,
              "2023-07-07": 7940385
            }
          },
          {
            "name": "Assets classified as held for sale",
            "note": null,
            "values": {
              "2024-07-07": null,
              "2023-07-07": null
            }
          },
          {
            "name": "Total current assets",
            "note": null,
            "values": {
              "2024-07-07": 25934878,
              "2023-07-07": 36138828
            }
          }
        ],
        "total_assets": {
          "2024-07-07": 709746026,
          "2023-07-07": 672187658
        }
      },
      "equity_and_liabilities": {
        "liabilities": {
          "non_current": [
            {
              "name": "Borrowings",
              "note": "17",
              "values": {
                "2024-07-07": 73348816,
                "2023-07-07": 305302467
              }
            },
            {
              "name": "Lease liabilities",
              "note": "11",
              "values": {
                "2024-07-07": 21077,
                "2023-07-07": 8390
              }
            },
            {
              "name": "Employee benefit obligations",
              "note": "18",
              "values": {
                "2024-07-07": 53635,
                "2023-07-07": 64483
              }
            },
            {
              "name": "Provisions",
              "note": "21",
              "values": {
                "2024-07-07": 69,
                "2023-07-07": 9666
              }
            },
            {
              "name": "Grants",
              "note": "26",
              "values": {
                "2024-07-07": 9538425,
                "2023-07-07": 3454812
              }
            },
            {
              "name": "Total non-current liabilities",
              "note": null,
              "values": {
                "2024-07-07": 82962022,
                "2023-07-07": 308839818
              }
            }
          ],
          "current": [
            {
              "name": "Borrowings",
              "note": "17",
              "values": {
                "2024-07-07": 30663349,
                "2023-07-07": 29072754
              }
            },
            {
              "name": "Employee benefit obligations",
              "note": "18",
              "values": {
                "2024-07-07": 27320,
                "2023-07-07": 14432
              }
            },
            {
              "name": "Trade and other payables",
              "note": "19",
              "values": {
                "2024-07-07": 33035264,
                "2023-07-07": 28549315
              }
            },
            {
              "name": "Contract liabilities",
              "note": "20",
              "values": {
                "2024-07-07": 82597,
                "2023-07-07": 453482
              }
            },
            {
              "name": "Provisions",
              "note": "21",
              "values": {
                "2024-07-07": 485221,
                "2023-07-07": 238898
              }
            },
            {
              "name": "Lease liabilities",
              "note": "11",
              "values": {
                "2024-07-07": 9236,
                "2023-07-07": 26178
              }
            },
            {
              "name": "Total current liabilities",
              "note": null,
              "values": {
                "2024-07-07": 64302987,
                "2023-07-07": 58355059
              }
            }
          ],
          "total_liabilities": {
            "2024-07-07": 147265009,
            "2023-07-07": 367194877
          }
        },
        "equity_attributable_to_owners": [
          {
            "name": "Capital",
            "note": "22",
            "values": {
              "2024-07-07": 586864060,
              "2023-07-07": 319246063
            }
          },
          {
            "name": "Legal reserve",
            "note": "23",
            "values": {
              "2024-07-07": 2283,
              "2023-07-07": 2283
            }
          },
          {
            "name": "Other reserves",
            "note": "24",
            "values": {
              "2024-07-07": -20859,
              "2023-07-07": -38648
            }
          },
          {
            "name": "Accumulated losses",
            "note": null,
            "values": {
              "2024-07-07": -187132306,
              "2023-07-07": -176984756
            }
          },
          {
            "name": "Non-distributable reserve",
            "note": "25",
            "values": {
              "2024-07-07": 162767839,
              "2023-07-07": 162767839
            }
          },
          {
            "name": "Total equity",
            "note": null,
            "values": {
              "2024-07-07": 562481017,
              "2023-07-07": 304992781
            }
          }
        ],
        "total_equity_and_liabilities": {
          "2024-07-07": 709746026,
          "2023-07-07": 672187658
        }
      }
    },
    "cash_flows": {
      "periods": [
        "2024-07-07",
        "2023-07-07"
      ],
      "line_items": [
        {
          "name": "Cash generated from (used in) operations",
          "note": "27(a)",
          "values": {
            "2024-07-07": 36942848,
            "2023-07-07": 17500764
          }
        },
        {
          "name": "Interest paid on borrowings",
          "note": "17",
          "values": {
            "2024-07-07": -4613919,
            "2023-07-07": -1284027
          }
        },
        {
          "name": "Interest paid on leases",
          "note": "11",
          "values": {
            "2024-07-07": -1524,
            "2023-07-07": -7283
          }
        },
        {
          "name": "Net cash from operating activities",
          "note": null,
          "values": {
            "2024-07-07": 32327405,
            "2023-07-07": 16209455
          }
        },
        {
          "name": "Purchase of property, plant and equipment",
          "note": "10",
          "values": {
            "2024-07-07": -39208187,
            "2023-07-07": -25168595
          }
        },
        {
          "name": "Purchase of intangible assets",
          "note": "14",
          "values": {
            "2024-07-07": -226379,
            "2023-07-07": 0
          }
        },
        {
          "name": "Payment for right of use assets",
          "note": "11",
          "values": {
            "2024-07-07": -7875,
            "2023-07-07": -510
          }
        },
        {
          "name": "Net cash from investing activities",
          "note": null,
          "values": {
            "2024-07-07": -39442441,
            "2023-07-07": -25169105
          }
        },
        {
          "name": "Proceeds from borrowings",
          "note": "17",
          "values": {
            "2024-07-07": 7016701,
            "2023-07-07": 13535739
          }
        },
        {
          "name": "Repayments of borrowings",
          "note": "17",
          "values": {
            "2024-07-07": -1980051,
            "2023-07-07": -5730016
          }
        },
        {
          "name": "Principal elements of lease payments",
          "note": null,
          "values": {
            "2024-07-07": -25988,
            "2023-07-07": -64969
          }
        },
        {
          "name": "Net cash from financing activities",
          "note": null,
          "values": {
            "2024-07-07": 5010662,
            "2023-07-07": 7740754
          }
        },
        {
          "name": "Net (decrease)/increase in cash and cash equivalents",
          "note": null,
          "values": {
            "2024-07-07": -2104373,
            "2023-07-07": -1218897
          }
        },
        {
          "name": "Cash and cash equivalents at beginning of year",
          "note": "16",
          "values": {
            "2024-07-07": 7940385,
            "2023-07-07": 10907444
          }
        },
        {
          "name": "Effects of exchange rate changes on cash and cash equivalents",
          "note": null,
          "values": {
            "2024-07-07": -2382917,
            "2023-07-07": -1748162
          }
        },
        {
          "name": "Cash and cash equivalents at end of year",
          "note": "16",
          "values": {
            "2024-07-07": 3453095,
            "2023-07-07": 7940385
          }
        }
      ]
    },
    "changes_in_equity": {
      "columns": [
        "Capital",
        "Legal reserve",
        "Other reserves",
        "Accumulated loss",
        "Non-distributable reserve",
        "Total equity"
      ],
      "rows": [
        {
          "label": "As at 8 July 2022",
          "values": {
            "Capital": 317387886,
            "Legal reserve": 2283,
            "Other reserves": -3660,
            "Accumulated loss": -152145959,
            "Non-distributable reserve": 162767839,
            "Total equity": 328008389
          }
        },
        {
          "label": "Loss for the period (year ended 7 July 2023)",
          "values": {
            "Capital": 0,
            "Legal reserve": 0,
            "Other reserves": 0,
            "Accumulated loss": -24838797,
            "Non-distributable reserve": 0,
            "Total equity": -24838797
          }
        },
        {
          "label": "Remeasurement gains on defined benefit plans (OCI) (year ended 7 July 2023)",
          "note": "18",
          "values": {
            "Capital": 0,
            "Legal reserve": 0,
            "Other reserves": -34988,
            "Accumulated loss": 0,
            "Non-distributable reserve": 0,
            "Total equity": -34988
          }
        },
        {
          "label": "Total comprehensive loss (year ended 7 July 2023)",
          "values": {
            "Capital": 0,
            "Legal reserve": 0,
            "Other reserves": -34988,
            "Accumulated loss": -24838797,
            "Non-distributable reserve": 0,
            "Total equity": -24873785
          }
        },
        {
          "label": "Capital contribution (year ended 7 July 2023)",
          "note": "22",
          "values": {
            "Capital": 1858177,
            "Legal reserve": 0,
            "Other reserves": 0,
            "Accumulated loss": 0,
            "Non-distributable reserve": 0,
            "Total equity": 1858177
          }
        },
        {
          "label": "As at 7 July 2023",
          "values": {
            "Capital": 319246063,
            "Legal reserve": 2283,
            "Other reserves": -38648,
            "Accumulated loss": -176984756,
            "Non-distributable reserve": 162767839,
            "Total equity": 304992781
          }
        },
        {
          "label": "Loss for the period (year ended 7 July 2024)",
          "values": {
            "Capital": 0,
            "Legal reserve": 0,
            "Other reserves": 0,
            "Accumulated loss": -10147553,
            "Non-distributable reserve": 0,
            "Total equity": -10147553
          }
        },
        {
          "label": "Remeasurement gains on defined benefit plans (OCI) (year ended 7 July 2024)",
          "note": "18",
          "values": {
            "Capital": 0,
            "Legal reserve": 0,
            "Other reserves": 17789,
            "Accumulated loss": 0,
            "Non-distributable reserve": 0,
            "Total equity": 17789
          }
        },
        {
          "label": "Total comprehensive loss (year ended 7 July 2024)",
          "values": {
            "Capital": 0,
            "Legal reserve": 0,
            "Other reserves": 17789,
            "Accumulated loss": -10147553,
            "Non-distributable reserve": 0,
            "Total equity": -10129764
          }
        },
        {
          "label": "Capital contribution (year ended 7 July 2024)",
          "note": "22",
          "values": {
            "Capital": 267617998,
            "Legal reserve": 0,
            "Other reserves": 0,
            "Accumulated loss": 0,
            "Non-distributable reserve": 0,
            "Total equity": 267617998
          }
        },
        {
          "label": "As at 7 July 2024",
          "values": {
            "Capital": 586864060,
            "Legal reserve": 2283,
            "Other reserves": -20859,
            "Accumulated loss": -187132306,
            "Non-distributable reserve": 162767839,
            "Total equity": 562481017
          }
        }
      ]
    }
  }
}